autobigs/engine/__init__.py
autobigs/engine/reading.py
autobigs/engine/writing.py
autobigs/engine/analysis/__init__.py
autobigs/engine/analysis/bigsdb.py
autobigs/engine/exceptions/__init__.py
autobigs/engine/exceptions/database.py
autobigs/engine/structures/__init__.py
autobigs/engine/structures/alignment.py
autobigs/engine/structures/genomics.py
autobigs/engine/structures/mlst.py
autobigs_engine-0.14.2.dist-info/LICENSE
autobigs_engine-0.14.2.dist-info/METADATA
autobigs_engine-0.14.2.dist-info/WHEEL
autobigs_engine-0.14.2.dist-info/top_level.txt
autobigs_engine-0.14.2.dist-info/RECORD
