Metadata-Version: 2.2
Name: autoBIGS.engine
Version: 0.14.2
Summary: A library to rapidly fetch fetch MLST profiles given sequences for various diseases.
License: GPL-3.0-or-later
Project-URL: Homepage, https://github.com/Syph-and-VPD-Lab/autoBIGS.engine
Project-URL: Source, https://github.com/Syph-and-VPD-Lab/autoBIGS.engine
Project-URL: Issues, https://github.com/Syph-and-VPD-Lab/autoBIGS.engine/issues
Requires-Python: >=3.12
License-File: LICENSE
Requires-Dist: biopython==1.85
Requires-Dist: aiohttp[speedups]==3.11.*
